can_log_analyzer/__init__.py
can_log_analyzer/app.py
can_log_analyzer/core/__init__.py
can_log_analyzer/core/analyzer.py
can_log_analyzer/ui/__init__.py
can_log_analyzer/ui/app_ui.py
can_log_analyzer-26.0.0.dist-info/WHEEL
can_log_analyzer-26.0.0.dist-info/METADATA
can_log_analyzer-26.0.0.dist-info/RECORD
