Metadata-Version: 2.3
Name: can_log_analyzer
Version: 26.0.0
Summary: CAN log Analyzer
Keywords: python,CAN,log,analyzer
Author: chaitu-ycr
Author-email: chaitu-ycr <chaitu.ycr@gmail.com>
License: MIT License
Classifier: Programming Language :: Python :: 3
Classifier: License :: OSI Approved :: MIT License
Requires-Dist: cantools
Requires-Dist: python-can
Requires-Dist: pandas
Requires-Dist: pyarrow
Requires-Dist: plotly
Requires-Dist: nicegui[native]
Requires-Dist: matplotlib
Requires-Python: >=3.10, <=3.14
Project-URL: homepage, https://github.com/chaitu-ycr/can-log-analyzer
Project-URL: repository, https://github.com/chaitu-ycr/can-log-analyzer/
Project-URL: documentation, https://chaitu-ycr.github.io/can-log-analyzer
